reoptimization_algorithms/__init__.py
reoptimization_algorithms/algorithms/__init__.py
reoptimization_algorithms/algorithms/unwtd_pvcp.py
reoptimization_algorithms/errors/BaseError.py
reoptimization_algorithms/errors/Error.py
reoptimization_algorithms/errors/__init__.py
reoptimization_algorithms/utils/__init__.py
reoptimization_algorithms/utils/graph/__init__.py
reoptimization_algorithms/utils/graph/base_edge.py
reoptimization_algorithms/utils/graph/base_graph.py
reoptimization_algorithms/utils/graph/base_vertex.py
reoptimization_algorithms/utils/graph/edge.py
reoptimization_algorithms/utils/graph/graph.py
reoptimization_algorithms/utils/graph/pvc.py
reoptimization_algorithms/utils/graph/undirected_graph.py
reoptimization_algorithms/utils/graph/vertex.py
reoptimization_algorithms-0.1.3.dist-info/LICENSE.txt
reoptimization_algorithms-0.1.3.dist-info/METADATA
reoptimization_algorithms-0.1.3.dist-info/WHEEL
reoptimization_algorithms-0.1.3.dist-info/top_level.txt
reoptimization_algorithms-0.1.3.dist-info/RECORD
