Metadata-Version: 2.1
Name: reoptimization-algorithms
Version: 0.1.3
Summary: Package implementing some well known Reoptimization algorithms
Home-page: https://mek97.github.io/reoptimization-algorithms/index.html
Author: Mehul Kumar
Author-email: mehul.k1997@gmail.com
License: MIT License
Project-URL: Bug Reports, https://github.com/mek97/reoptimization-algorithms/issues
Project-URL: Source, https://github.com/mek97/reoptimization-algorithms
Keywords: Reoptimization Approximation Algorithms Path vertex cover
Platform: UNKNOWN
Classifier: Programming Language :: Python :: 3.6
Classifier: Programming Language :: Python :: 3.7
Classifier: Programming Language :: Python :: 3.8
Requires-Python: >=3.6
Provides-Extra: dev
Requires-Dist: check-manifest ; extra == 'dev'
Provides-Extra: test
Requires-Dist: coverage ; extra == 'test'
